edwh_demo_tasks_plugin/__about__.py
edwh_demo_tasks_plugin/__init__.py
edwh_demo_tasks_plugin/demo_plugin.py
edwh_demo_tasks_plugin-0.0.5.dist-info/METADATA
edwh_demo_tasks_plugin-0.0.5.dist-info/WHEEL
edwh_demo_tasks_plugin-0.0.5.dist-info/entry_points.txt
edwh_demo_tasks_plugin-0.0.5.dist-info/licenses/LICENSE.txt
edwh_demo_tasks_plugin-0.0.5.dist-info/RECORD
