Metadata-Version: 2.1
Name: edwh-demo-tasks-plugin
Version: 0.0.5
Summary: Demo project with a plugin to be discovered from the edwh package
Project-URL: Documentation, https://github.com/remcoboerma/edwh-demo-tasks-plugin#readme
Project-URL: Issues, https://github.com/remcoboerma/edwh-demo-tasks-plugin/issues
Project-URL: Source, https://github.com/remcoboerma/edwh-demo-tasks-plugin
Author-email: Remco Boerma <remco.b@educationwarehouse.nl>
License-Expression: MIT
License-File: LICENSE.txt
Classifier: Development Status :: 4 - Beta
Classifier: Programming Language :: Python
Classifier: Programming Language :: Python :: 3.7
Classifier: Programming Language :: Python :: 3.8
Classifier: Programming Language :: Python :: 3.9
Classifier: Programming Language :: Python :: 3.10
Classifier: Programming Language :: Python :: 3.11
Classifier: Programming Language :: Python :: Implementation :: CPython
Classifier: Programming Language :: Python :: Implementation :: PyPy
Requires-Python: >=3.7
Requires-Dist: invoke
